setup.py
rax_scheduled_images_python_novaclient_ext/__init__.py
rax_scheduled_images_python_novaclient_ext.egg-info/PKG-INFO
rax_scheduled_images_python_novaclient_ext.egg-info/SOURCES.txt
rax_scheduled_images_python_novaclient_ext.egg-info/dependency_links.txt
rax_scheduled_images_python_novaclient_ext.egg-info/requires.txt
rax_scheduled_images_python_novaclient_ext.egg-info/top_level.txt