Metadata-Version: 1.1
Name: rax-scheduled-images-python-novaclient-ext
Version: 0.3.1
Summary: Extends python-novaclient to use RAX-SI, the Rackspace Nova API Scheduled Images extension
Home-page: https://github.com/rackspace-titan/rax_scheduled_images_python_novaclient_ext
Author: Rackspace
Author-email: eddie.sheffield@rackspace.com
License: Apache License, Version 2.0
Platform: UNKNOWN
Classifier: Development Status :: 4 - Beta
Classifier: Intended Audience :: Developers
Classifier: Intended Audience :: Information Technology
Classifier: License :: OSI Approved :: Apache Software License
Classifier: Operating System :: OS Independent
Classifier: Programming Language :: Python
